PySimpleBarcode/PySimpleBarcode.py
PySimpleBarcode/__init__.py
PySimpleBarcode-0.1.2.dist-info/LICENSE
PySimpleBarcode-0.1.2.dist-info/METADATA
PySimpleBarcode-0.1.2.dist-info/WHEEL
PySimpleBarcode-0.1.2.dist-info/top_level.txt
PySimpleBarcode-0.1.2.dist-info/RECORD
