Metadata-Version: 2.1
Name: PySimpleBarcode
Version: 0.1.2
Summary: A small Code 39 barcode generator using PIL and the Libre Barcode 39 font family
Home-page: https://github.com/AndrewSpangler/PySimpleBarcode
Author: Andrew Spangler
Author-email: Andrew Spangler <AndrewSpangler@users.noreply.github.com>
Project-URL: Homepage, https://github.com/AndrewSpangler/PySimpleBarcode
Project-URL: Bug Tracker, https://github.com/AndrewSpangler/PySimpleBarcode/issues
Keywords: barcode,code39,code,39,generator
Classifier: Programming Language :: Python :: 3
Classifier: License :: OSI Approved :: GNU General Public License v3 or later (GPLv3+)
Classifier: Operating System :: OS Independent
Requires-Python: >=3.8
License-File: LICENSE
Requires-Dist: pillow
